test_project/__init__.py
test_project/settings.py
test_project/urls.py
test_project/dressings/__init__.py
test_project/dressings/models.py
test_project/dressings/migrations/0001_initial.py
test_project/dressings/migrations/__init__.py
vinaigrette/__init__.py
vinaigrette/middleware.py
vinaigrette/management/__init__.py
vinaigrette/management/commands/__init__.py
vinaigrette/management/commands/makemessages.py
django_vinaigrette-2.0.1.dist-info/LICENSE
django_vinaigrette-2.0.1.dist-info/METADATA
django_vinaigrette-2.0.1.dist-info/WHEEL
django_vinaigrette-2.0.1.dist-info/top_level.txt
django_vinaigrette-2.0.1.dist-info/RECORD
