Metadata-Version: 2.1
Name: django-vinaigrette
Version: 2.0.1
Summary: Translate Django model data using gettext
Home-page: https://github.com/ecometrica/django-vinaigrette/
Author: Ecometrica Ltd
Author-email: software@ecometrica.com
License: UNKNOWN
Keywords: django,translation,gettext,internationalization,i18n,database,model
Platform: UNKNOWN
Classifier: Programming Language :: Python
Classifier: Programming Language :: Python :: 3.6
Classifier: Programming Language :: Python :: 3.7
Classifier: Development Status :: 4 - Beta
Classifier: License :: OSI Approved :: BSD License
Classifier: Operating System :: POSIX
Classifier: Topic :: Software Development :: Internationalization
Classifier: Framework :: Django
Classifier: Framework :: Django :: 1.11
Classifier: Framework :: Django :: 2.0
Classifier: Framework :: Django :: 2.1
